tests/__init__.py
tests/test_createTask.py
tests/test_getBalance.py
tests/test_getServices.py
tests/test_getTasks.py
vkmix/__init__.py
vkmix/vkmix.py
vkmix-1.5.dist-info/LICENSE
vkmix-1.5.dist-info/METADATA
vkmix-1.5.dist-info/WHEEL
vkmix-1.5.dist-info/top_level.txt
vkmix-1.5.dist-info/RECORD
